[
{
"name": "Derrick Cordell",
"totalSales": 100,
"salesPeriod": 10,
"experienceMultiplier": 0.5
},
{
"name": "Derick Shae",
"totalSales": 110,
"salesPeriod": 10,
"experienceMultiplier": 0.5
},
{
"name": "Cathleen Nita",
"totalSales": 120,
"salesPeriod": 10,
"experienceMultiplier": 0.5
},
{
"name": "Mora Sherman",
"totalSales": 130,
"salesPeriod": 10,
"experienceMultiplier": 0.5
},
{
"name": "Mora Sherman",
"totalSales": 140,
"salesPeriod": 10,
"experienceMultiplier": 0.5
},
{
"name": "Brittny Charlene",
"totalSales": 150,
"salesPeriod": 10,
"experienceMultiplier": 0.5
},
{
"name": "Brant Rolland",
"totalSales": 80,
"salesPeriod": 10,
"experienceMultiplier": 0.5
},
{
"name": "Brant Rolland",
"totalSales": 90,
"salesPeriod": 10,
"experienceMultiplier": 0.5
},
{
"name": "Bernadine Noel",
"totalSales": 60,
"salesPeriod": 10,
"experienceMultiplier": 0.5
},
{
"name": "Ben Caleigh",
"totalSales": 140,
"salesPeriod": 10,
"experienceMultiplier": 0.5
},
{
"name": "Ben Caleigh",
"totalSales": 140,
"salesPeriod": 10,
"experienceMultiplier": 0.5
},
{
"name": "Livia Patsy",
"totalSales": 140,
"salesPeriod": 10,
"experienceMultiplier": 0.5
},
{
"name": "Brenton Boone",
"totalSales": 140,
"salesPeriod": 10,
"experienceMultiplier": 0.5
},
{
"name": "Wallace Bishop",
"totalSales": 140,
"salesPeriod": 10,
"experienceMultiplier": 0.5
},
{
"name": "Tilda Macey",
"totalSales": 140,
"salesPeriod": 10,
"experienceMultiplier": 0.5
},
{
"name": "Marjory Chas",
"totalSales": 140,
"salesPeriod": 10,
"experienceMultiplier": 0.5
},
{
"name": "Cheryl Bram",
"totalSales": 140,
"salesPeriod": 10,
"experienceMultiplier": 0.5
},
{
"name": "Jessika Lamont",
"totalSales": 140,
"salesPeriod": 10,
"experienceMultiplier": 0.5
},
{
"name": "Tatiana Dax",
"totalSales": 140,
"salesPeriod": 10,
"experienceMultiplier": 0.5
},
{
"name": "Tatiana Dax",
"totalSales": 140,
"salesPeriod": 10,
"experienceMultiplier": 0.5
}
]